{
    "акт": {
        "id": 1,
        "label": "акт",
        "aliases": []
    },
    "договор дарения": {
        "id": 19,
        "label": "договор дарения",
        "aliases": [
            "догвор дарения"
        ]
    },
    "договор купли-продажи": {
        "id": 3,
        "label": "договор купли-продажи",
        "aliases": [
            "договор купли продажи",
            "договор  купли продажи",
            "договор купл продажи",
            "документы купли-продажи"
        ]
    },
    "договор": {
        "id": 4,
        "label": "договор",
        "aliases": [
            "договро",
            "догоовр",
            "догвоор"
        ]
    },
    "документы владельцев": {
        "id": 5,
        "label": "документы владельцев",
        "aliases": [
            "документ владельцев"
        ]
    },
    "заявление о гос рег": {
        "id": 6,
        "label": "заявление о гос рег",
        "aliases": [
            "заявленеие о гос рег",
            "заявление гос рег",
            "заяление о гос рег"
        ]
    },
    "квитанция": {
        "id": 7,
        "label": "квитанция",
        "aliases": [
            "квитанций",
            "квитанции",
            "квитанци"
        ]
    },
    "постановление о наложении ареста": {
        "id": 8,
        "label": "постановление о наложении ареста",
        "aliases": [
            "постановление наложении ареста",
            "постановление наложении запрета",
            "постановление о наложение ареста",
            "постановление о наложении запрета"
        ]
    },
    "постановление": {
        "id": 9,
        "label": "постановление",
        "aliases": [
            "постановлениеа"
        ]
    },
    "свидетельство о праве на наследство": {
        "id": 10,
        "label": "свидетельство о праве на наследство",
        "aliases": [
            "свидетельство о наследстве",
            "свидетельство о праве наследства",
            "свидетельство о праве наследство",
            "свидетельство наследстве",
            "свидетельство о праве наследстве",
            "свидетельство наследство",
            "свидетельсто о праве на наследство",
            "свидетельство на наследство",
            "свидетельство о наследство"
        ]
    },
    "тех паспорт": {
        "id": 11,
        "label": "тех паспорт",
        "aliases": [
            "пасп"
        ]
    },
    "договор о приватизации": {
        "id": 12,
        "label": "договор о приватизации",
        "aliases": [
            "договор приватизации",
            "договор приват"
        ]
    },
    "заключение об изменение площади": {
        "id": 13,
        "label": "заключение об изменение площади",
        "aliases": [
            "заключение об измене площ",
            "заключение об изменение площ",
            "заключение измене площ",
            "заключеник об измене площ",
            "заключение об измене площади",
            "заключение о измене площ",
            "заключение об изменении площади"
        ]
    },
    "уведомление о гос рег": {
        "id": 14,
        "label": "уведомление о гос рег",
        "aliases": [
            "увед о гос рег",
            "уведомление об гос рег"
        ]
    },
    "эл чек": {
        "id": 15,
        "label": "эл чек",
        "aliases": [
            "элчек",
            "элч ек",
            "чек"
        ]
    },
    "заявление": {
        "id": 16,
        "label": "заявление",
        "aliases": []
    },
    "эцп договора": {
        "id": 17,
        "label": "эцп договора",
        "aliases": [
            "эцп договор",
            "эцп догоовра",
            "эцп догоовр"
        ]
    },
    "доверенность": {
        "id": 18,
        "label": "доверенность",
        "aliases": []
    },
    "договор залога": {
        "id": 20,
        "label": "договор залога",
        "aliases": [
            "договор о залоге",
            "договор залог",
            "догвор залога"
        ]
    },
    "договор на оказание услуг": {
        "id": 21,
        "label": "договор на оказание услуг",
        "aliases": [
            "договор на оказ услуг",
            "договор оказ услуг",
            "договор оказание услуг",
            "договор об оказании услуг"
        ]
    },
    "уведомление о выполнении обязательств": {
        "id": 22,
        "label": "уведомление о выполнении обязательств",
        "aliases": [
            "уведомление ипол обяз",
            "уведомление о выполнение обяз",
            "уведомление вып обяз",
            "уведомление о вып обяз",
            "уведомление об исполнении обязательств",
            "уведомление о полном выполнении обяз",
            "увдомление о выполнение обязательств",
            "увед о вып обяз"
        ]
    },
    "рег удостоверение": {
        "id": 23,
        "label": "рег удостоверение",
        "aliases": [
            "рег удостоворние",
            "рег удостоверение",
            "рег удостоверенение"
        ]
    },
    "ипотечное свидетельство": {
        "id": 24,
        "label": "ипотечное свидетельство",
        "aliases": []
    },
    "уведомление о невыполнении обязательств": {
        "id": 25,
        "label": "уведомление о невыполнении обязательств",
        "aliases": [
            "уведомлени невып обяз",
            "уведомлени о невып обяз",
            "уведомление невып обяз",
            "уведомление о невып обяз",
            "уведомление о невыполнении обязанностей",
            "уведомление о невыполнении обязательств",
            "увед о невып обяз"
        ]
    },
    "уведомление о снятии обременения": {
        "id": 26,
        "label": "уведомление о снятии обременения",
        "aliases": [
            "уведомление о снятии обременение",
            "уведомление о снятия обременения",
            "уведомление для снятии обременения"
        ]
    },
    "документ": {
        "id": 27,
        "label": "документ",
        "aliases": []
    },
    "договор мены": {
        "id": 28,
        "label": "договор мены",
        "aliases": []
    },
    "доп соглашение": {
        "id": 29,
        "label": "доп соглашение",
        "aliases": []
    },
    "протокол согласования залога": {
        "id": 30,
        "label": "протокол согласования залога",
        "aliases": [
            "протокол согласования",
            "протокол согласование",
            "протокол согласавание",
            "протакол согласование"
        ]
    },
    "свидетельство о праве собственности": {
        "id": 31,
        "label": "свидетельство о праве собственности",
        "aliases": [
            "свидетельство о право собственности"
        ]
    },
    "справка": {
        "id": 32,
        "label": "справка",
        "aliases": []
    },
    "акт приема": {
        "id": 33,
        "label": "акт приема",
        "aliases": [
            "акт приеа",
            "акт приемки",
            "аки приема"
        ]
    },
    "погашение залога": {
        "id": 34,
        "label": "погашение залога",
        "aliases": [
            "погашения залога"
        ]
    },
    "постановление о снятии ареста": {
        "id": 35,
        "label": "постановление о снятии ареста",
        "aliases": [
            "постановление снятии ареста"
        ]
    },
    "сведения о собственнике": {
        "id": 36,
        "label": "сведения о собственнике",
        "aliases": [
            "сведения о собственника",
            "сведения собственника",
            "сведение о собственнике"
        ]
    },
    "уведомление": {
        "id": 37,
        "label": "уведомление",
        "aliases": []
    },
    "ипотечный договор": {
        "id": 38,
        "label": "ипотечный договор",
        "aliases": [
            "договор ипотеки",
            "договор об ипотеке"
        ]
    },
    "определение": {
        "id": 39,
        "label": "определение",
        "aliases": []
    },
    "уведомление об отказе в гос рег": {
        "id": 40,
        "label": "уведомление об отказе в гос рег",
        "aliases": [
            "уведомление отказа гос рег",
            "уведомление об отказе гос рег",
            "уведомление отказе гос рег",
            "уведомление об отказ гос рег",
            "отказ от гос рег",
            "уведомление об отказе от гос рег",
            "отказ о гос рег",
            "увед об отказ гос рег",
            "увед об отказе гос рег",
            "увед об отказе в гос рег",
            "увед отказ от гос рег",
            "увед отказ гос рег",
            "об отказе в гос рег",
            "уведомление о рег"
        ]
    },
    "договор об аренде": {
        "id": 41,
        "label": "договор об аренде",
        "aliases": [
            "об отказе от гос рег"
        ]
    },
    "исполнительный лист": {
        "id": 42,
        "label": "исполнительный лист",
        "aliases": []
    },
    "заключение": {
        "id": 43,
        "label": "заключение",
        "aliases": []
    },
    "информационная справка": {
        "id": 44,
        "label": "информационная справка",
        "aliases": []
    },
    "согласие на персональные данные": {
        "id": 45,
        "label": "согласие на персональные данные",
        "aliases": []
    },
    "договор обмена": {
        "id": 46,
        "label": "договор обмена",
        "aliases": [
            "договор об обмене"
        ]
    },
    "предложение о исполнение постановление": {
        "id": 47,
        "label": "предложение о исполнение постановление",
        "aliases": []
    },
    "договор аренды": {
        "id": 48,
        "label": "договор аренды",
        "aliases": []
    },
    "соглашение о расторжении договора аренды": {
        "id": 49,
        "label": "соглашение о расторжении договора аренды",
        "aliases": [
            "соглашение о расторжении аренды"
        ]
    },
    "заочное решение": {
        "id": 50,
        "label": "заочное решение",
        "aliases": []
    },
    "уведомление о проведение торгов": {
        "id": 51,
        "label": "уведомление о проведение торгов",
        "aliases": [
            "уведомление о торгов",
            "уведомление торгов",
            "уведомление проведение торгов",
            "уведомление пров торгов",
            "уведомление проведение торг",
            "уведомление о проведении торгов"
        ]
    },
    "соглашение о расторжении договора купли-продажи": {
        "id": 52,
        "label": "соглашение о расторжении договора купли-продажи",
        "aliases": [
            "соглашение о расторжении договора купли продажи"
        ]
    },
    "договор уступки прав требования": {
        "id": 53,
        "label": "договор уступки прав требования",
        "aliases": [
            "договор уступки прав",
            "уступки права требования",
            "уступки права тебования"
        ]
    },
    "протокол легализации": {
        "id": 54,
        "label": "протокол легализации",
        "aliases": []
    },
    "решение о легализации": {
        "id": 55,
        "label": "решение о легализации",
        "aliases": []
    },
    "прекрашение залога": {
        "id": 56,
        "label": "прекрашение залога",
        "aliases": [
            "прекращение залога"
        ]
    },
    "свидетельство о гос рег": {
        "id": 57,
        "label": "свидетельство о гос рег",
        "aliases": [
            "свидетельство о рег",
            "свид о гос рег",
            "свидетельство гос рег"
        ]
    },
    "соглашение о расторжении договора": {
        "id": 58,
        "label": "соглашение о расторжении договора",
        "aliases": []
    },
    "решение об ограничении": {
        "id": 59,
        "label": "решение об ограничении",
        "aliases": []
    },
    "извещение": {
        "id": 60,
        "label": "извещение",
        "aliases": []
    },
    "уведомление о замены залога": {
        "id": 61,
        "label": "уведомление о замены залога",
        "aliases": []
    },
    "регистрация залога": {
        "id": 62,
        "label": "регистрация залога",
        "aliases": []
    },
    "предложение": {
        "id": 63,
        "label": "предложение",
        "aliases": []
    },
    "решение": {
        "id": 64,
        "label": "решение",
        "aliases": []
    },
    "уведомление о снятии ареста": {
        "id": 65,
        "label": "уведомление о снятии ареста",
        "aliases": []
    },
    "ордер": {
        "id": 66,
        "label": "ордер",
        "aliases": []
    },
    "справка о гос рег": {
        "id": 67,
        "label": "справка о гос рег",
        "aliases": []
    },
    "предаточный акт": {
        "id": 68,
        "label": "предаточный акт",
        "aliases": []
    },
    "соглашение о расторжении договора о залоге": {
        "id": 69,
        "label": "соглашение о расторжении договора о залоге",
        "aliases": []
    },
    "протокол согласования": {
        "id": 70,
        "label": "протокол согласования",
        "aliases": []
    },
    "соглашение": {
        "id": 71,
        "label": "соглашение",
        "aliases": []
    },
    "разрешение": {
        "id": 72,
        "label": "разрешение",
        "aliases": []
    },
    "протокол": {
        "id": 73,
        "label": "протокол",
        "aliases": []
    },
    "свидетельство": {
        "id": 74,
        "label": "свидетельство",
        "aliases": []
    },
    "апелляционное решение": {
        "id": 75,
        "label": "апелляционное решение",
        "aliases": []
    },
    "кассационная жалоба": {
        "id": 76,
        "label": "кассационная жалоба",
        "aliases": []
    },
    "отзыв": {
        "id": 77,
        "label": "отзыв",
        "aliases": []
    },
    "договор займа": {
        "id": 78,
        "label": "договор займа",
        "aliases": []
    },
    "протокол согласования комиссии": {
        "id": 79,
        "label": "протокол согласования комиссии",
        "aliases": []
    }
}